project/__init__.py
project/app.py
project/loader.py
project/model/__init__.py
project/model/final.enc
project/model/scaler.enc
research_tool-0.1.2.3.dist-info/METADATA
research_tool-0.1.2.3.dist-info/WHEEL
research_tool-0.1.2.3.dist-info/entry_points.txt
research_tool-0.1.2.3.dist-info/top_level.txt
research_tool-0.1.2.3.dist-info/RECORD
