Metadata-Version: 2.4
Name: Research_Tool
Version: 0.1.2.3
Summary: Offline Vexp Predictor GUI
Author: Shashwat Shukla
License: MIT
Keywords: machine-learning,engineering,gui,offline,vexp
Requires-Python: >=3.9
Requires-Dist: numpy
Requires-Dist: scikit-learn
Requires-Dist: joblib
Requires-Dist: lightgbm
Requires-Dist: catboost
Requires-Dist: cryptography
